vtds_application_openchami/__init__.py
vtds_application_openchami/private/__init__.py
vtds_application_openchami/private/application.py
vtds_application_openchami/private/config.py
vtds_application_openchami/private/config/README.md
vtds_application_openchami/private/config/config.yaml
vtds_application_openchami/private/config/test_overlay.yaml
vtds_application_openchami/private/templates/bare/prepare_node.sh
vtds_application_openchami/private/templates/blade/nginx-default-site-config
vtds_application_openchami/private/templates/blade/prepare_blade.sh
vtds_application_openchami/private/templates/blade/sushy-emulator.conf
vtds_application_openchami/private/templates/blade/sushy-emulator.service
vtds_application_openchami/private/templates/quadlet/Corefile
vtds_application_openchami/private/templates/quadlet/OpenCHAMI-Prepare.sh
vtds_application_openchami/private/templates/quadlet/boot-compute-debug.yaml
vtds_application_openchami/private/templates/quadlet/build-image.sh
vtds_application_openchami/private/templates/quadlet/compute-base-rocky9.yaml
vtds_application_openchami/private/templates/quadlet/compute-debug-rocky9.yaml
vtds_application_openchami/private/templates/quadlet/containers.conf
vtds_application_openchami/private/templates/quadlet/coredhcp.yaml
vtds_application_openchami/private/templates/quadlet/minio.container
vtds_application_openchami/private/templates/quadlet/nodes.yaml
vtds_application_openchami/private/templates/quadlet/prep_setup.sh
vtds_application_openchami/private/templates/quadlet/prepare_node.sh
vtds_application_openchami/private/templates/quadlet/registry.container
vtds_application_openchami/private/templates/quadlet/rocky-base-9.yaml
vtds_application_openchami/private/templates/quadlet/s3-public-read-boot-images.json
vtds_application_openchami/private/templates/quadlet/s3-public-read-efi.json
vtds_application_openchami/private/templates/quadlet/s3cfg
vtds_application_openchami-0.0.11.dist-info/licenses/LICENSE
vtds_application_openchami-0.0.11.dist-info/METADATA
vtds_application_openchami-0.0.11.dist-info/WHEEL
vtds_application_openchami-0.0.11.dist-info/top_level.txt
vtds_application_openchami-0.0.11.dist-info/RECORD
